{
  "token": "your_token",
  "discordUrl": "https://discord.com/oauth2/authorize?client_id=792410047257772063&permissions=8&scope=bot",
  "repository": "https://github.com/scorixear/sun_management",
  "botPrefix": "!",
  "trackedGuilds": ["SUN", "SUN-Alts"],
  "saveRoles": ["Albion Officer", "Captains", "Quartermaster", "Sun Council", "Recruiter"],
  "language": "en-EN",
  "registerChannel": "register-channel",
  "removeChannel": "remove-channel",
  "ignoreRole": "sun_management_ignore",
  "dbhost": "127.0.0.1",
  "dbuser": "username",
  "dbpassword": "password",
  "dbport": "3306",
  "dbDataBase": "sunmanagement"
}